CHANGES.rst
MANIFEST.in
README.rst
setup.cfg
setup.py
documentation/API.rst
documentation/Makefile
documentation/conf.py
documentation/index.rst
example/Hello_World.py
mod_oled_128x64.egg-info/PKG-INFO
mod_oled_128x64.egg-info/SOURCES.txt
mod_oled_128x64.egg-info/dependency_links.txt
mod_oled_128x64.egg-info/requires.txt
mod_oled_128x64.egg-info/top_level.txt
oled/Font.py
oled/Graphics.py
oled/OLED.py
oled/__init__.py