Metadata-Version: 1.1
Name: mod-oled-128x64
Version: 0.0.5
Summary: Control module for MOD-OLED-128x64
Home-page: https://github.com/StefanMavrodiev/pyMOD-OLED
Author: Stefan Mavrodiev
Author-email: support@olimex.com
License: GPL2
Keywords: oled OLinuXino
Platform: ARM
Classifier: Development Status :: 4 - Beta
Classifier: Intended Audience :: Developers
Classifier: Intended Audience :: Science/Research
Classifier: Topic :: Scientific/Engineering :: Visualization
Classifier: License :: OSI Approved :: GNU General Public License v2 (GPLv2)
Classifier: Programming Language :: Python :: 2
Classifier: Programming Language :: Python :: 2.7
Classifier: Programming Language :: Python :: 3
Classifier: Programming Language :: Python :: 3.4
